libsnew
